<?xml version="1.0" encoding="UTF-8"?>
<web-app xmlns:xsi="http://www.w3.org/2001/XMLSchema-instance" xmlns="http://java.sun.com/xml/ns/javaee" xsi:schemaLocation="http://java.sun.com/xml/ns/javaee http://java.sun.com/xml/ns/javaee/web-app_2_5.xsd" id="WebApp_ID" version="2.5">
  <display-name>prto3</display-name>
  <welcome-file-list>
    <welcome-file>index.html</welcome-file>
    <welcome-file>index.htm</welcome-file>
    <welcome-file>index.jsp</welcome-file>
    <welcome-file>default.html</welcome-file>
    <welcome-file>default.htm</welcome-file>
    <welcome-file>default.jsp</welcome-file>
  </welcome-file-list>

  <servlet>
    <description></description>
    <display-name>hello</display-name>
    <servlet-name>hello</servlet-name>
    <servlet-class>srv1.hello</servlet-class>
  </servlet>
  <servlet-mapping>
    <servlet-name>hello</servlet-name>
    <url-pattern>/hello</url-pattern>
  </servlet-mapping>
  <servlet>

    <description></description>
    <display-name>hello2</display-name>
    <servlet-name>hello2</servlet-name>
    <servlet-class>srv1.hello2</servlet-class>
  </servlet>
  <servlet-mapping>
    <servlet-name>hello2</servlet-name>
    <url-pattern>/hello2</url-pattern>
  </servlet-mapping>

  <servlet>
    <description></description>
    <display-name>hello3</display-name>
    <servlet-name>hello3</servlet-name>
    <servlet-class>srv1.hello3</servlet-class>
  </servlet>
  <servlet-mapping>
    <servlet-name>hello3</servlet-name>
    <url-pattern>/hello3</url-pattern>
  </servlet-mapping>

  <servlet>
    <description></description>
    <display-name>mysrv</display-name>
    <servlet-name>mysrv</servlet-name>
    <servlet-class>srv1.mysrv</servlet-class>
  </servlet>
  <servlet-mapping>
    <servlet-name>mysrv</servlet-name>
    <url-pattern>/mysrv</url-pattern>
  </servlet-mapping>

    <servlet>
    <description></description>
    <display-name>book3Svlt</display-name>
    <servlet-name>book3Svlt</servlet-name>
    <servlet-class>srv1.book3Svlt</servlet-class>
  </servlet>
  <servlet-mapping>
    <servlet-name>book3Svlt</servlet-name>
    <url-pattern>/book3Svlt</url-pattern>
  </servlet-mapping>

</web-app>